pwnv/__init__.py
pwnv/constants.py
pwnv/cli/__init__.py
pwnv/cli/challenge.py
pwnv/cli/ctf.py
pwnv/cli/init.py
pwnv/cli/plugin.py
pwnv/cli/reset.py
pwnv/cli/solve.py
pwnv/core/__init__.py
pwnv/core/plugin_manager.py
pwnv/core/setup.py
pwnv/models/__init__.py
pwnv/models/challenge.py
pwnv/models/ctf.py
pwnv/models/init.py
pwnv/plugins/__init__.py
pwnv/plugins/plugin.py
pwnv/utils/__init__.py
pwnv/utils/config.py
pwnv/utils/crud.py
pwnv/utils/guards.py
pwnv/utils/plugin.py
pwnv/utils/remote.py
pwnv/utils/ui.py
pwnv-0.4.4.dist-info/licenses/LICENSE
pwnv-0.4.4.dist-info/METADATA
pwnv-0.4.4.dist-info/WHEEL
pwnv-0.4.4.dist-info/entry_points.txt
pwnv-0.4.4.dist-info/top_level.txt
pwnv-0.4.4.dist-info/RECORD
