Metadata-Version: 2.4
Name: pwnv
Version: 0.4.4
Summary: CLI tool for CTF management
Author-email: Shayan Alinejad <shayan.alinejad@proton.me>
License: MIT
Project-URL: Repository, https://github.com/CarixoHD/pwnv/
Project-URL: Issues, https://github.com/CarixoHD/pwnv/issues
Requires-Python: >=3.12
License-File: LICENSE
Requires-Dist: ctfbridge>=0.2.1
Requires-Dist: dotenv>=0.9.9
Requires-Dist: filelock>=3.18.0
Requires-Dist: inquirer>=3.4.0
Requires-Dist: inquirerpy>=0.3.4
Requires-Dist: pydantic>=2.10.3
Requires-Dist: typer>=0.15.1
Provides-Extra: dev
Requires-Dist: mypy; extra == "dev"
Requires-Dist: ruff; extra == "dev"
Requires-Dist: pre-commit; extra == "dev"
Dynamic: license-file
